<?xml version="1.0" encoding="UTF-8"?>
<entity-mappings version="2.1"
	xmlns="http://xmlns.jcp.org/xml/ns/persistence/orm" xmlns:xsi="http://www.w3.org/2001/XMLSchema-instance"
	xsi:schemaLocation="http://xmlns.jcp.org/xml/ns/persistence/orm http://xmlns.jcp.org/xml/ns/persistence/orm_2_1.xsd">

	<embeddable class="com.lapsa.insurance.domain.CalculationData">
		<attributes>
			<basic name="calculatedPremiumCost">
				<column name="CALCULATED_PERMIUM_COST" />
			</basic>
			<basic name="discountAmount">
				<column name="DISCOUNT_AMOUNT" />
			</basic>
			<basic name="actualPremiumCost">
				<column name="ACTUAL_PERMIUM_COST" />
			</basic>
			<basic name="premiumCurrency">
				<column name="PREMIUM_CURRENCY" />
				<enumerated>STRING</enumerated>
			</basic>
		</attributes>
	</embeddable>

</entity-mappings>